{"immagine": "https://www.comune.rovereto.tn.it/var/rovereto/storage/images/applicazioni2/openagenda/eventi/film28/1717450-1-ita-IT/film.jpg", "url": "https://www.comune.rovereto.tn.it/openpa/object/132720", "abstract_text": "Cinema Estate 2021", "abstract": "<p>Cinema Estate 2021</p>", "title": "La vita che verr\u00e0 - Her  di Phyllida Lloyd", "lon": "11.044773", "modifica": "2021-07-12", "link": "http://www.comune.rovereto.tn.it/api/opendata/v2/content/read/132720", "lat": "45.894645", "duration_days": "[datetime.date(2021, 8, 18), datetime.date(2021, 8, 18)]", "duration_hours": "('20:45', '22:25')", "weekday": "['mercoled\u00ec']", "indirizzo": "['dalle', 'alle', 'Giardino', 'delle', 'sculture', 'del', 'Mart', 'corso', 'Bettini', '43']", "repeated": "False", "ticket": [], "is_online": false, "is_offline": false, "is_blended": false}