{"indirizzo": "gioved\u00ec 22 luglio 2021   dalle 21 alle 22.30 Giardino Chiesa di S. Osvaldo via Santa Maria", "immagine": "https://www.comune.rovereto.tn.it/var/rovereto/storage/images/applicazioni2/openagenda/eventi/performance-scenica/1717943-1-ita-IT/performance-scenica.jpg", "url": "https://www.comune.rovereto.tn.it/openpa/object/132736", "abstract_text": "Una performance scenica di grande suggestione emotiva, tra teatro, poesia, parole e musica elettronica.", "abstract": "<p>Una performance scenica di grande suggestione emotiva, tra teatro, poesia, parole e musica elettronica.</p>", "nome": "I Campi Magnetici - Teatro - Musica - Parola  ANNULLATO", "lon": "11.044924", "modifica": "2021-07-22", "link": "http://www.comune.rovereto.tn.it/api/opendata/v2/content/read/132736", "lat": "45.885524", "is_online": false, "is_offline": true, "is_blended": false, "ticket": []}