{"immagine": "https://www.comune.rovereto.tn.it/var/rovereto/storage/images/applicazioni2/openagenda/eventi/rassegna-teatrale-al-castello-di-rovereto2/1612825-1-ita-IT/Rassegna-teatrale-al-Castello-di-Rovereto.jpg", "url": "https://www.comune.rovereto.tn.it/openpa/object/127625", "abstract_text": "Spettacolo di teatro", "abstract": "<p>Spettacolo di teatro</p>", "title": "Il Castello in scena - Una guerra da niente", "lon": "11.046312", "modifica": "2020-10-22", "link": "http://www.comune.rovereto.tn.it/api/opendata/v2/content/read/127625", "lat": "45.886317", "duration_days": "[datetime.date(2020, 10, 24), datetime.date(2020, 10, 7)]", "duration_hours": "('15:00', '18:00')", "weekday": "['sabato']", "indirizzo": "['Primo', 'spettacolo', 'ore', '|', 'Secondo', 'spettacolo', 'ore', 'Museo', 'Storico', 'Italiano', 'della', 'Guerra', 'Via', 'Castelbarco,']", "repeated": "False", "ticket": [], "is_online": false, "is_offline": true, "is_blended": false}