{"immagine": "https://www.comune.rovereto.tn.it/var/rovereto/storage/images/applicazioni2/openagenda/eventi/ciclo-di-conferenze-online3/1697746-3-ita-IT/Ciclo-di-conferenze-online.png", "url": "https://www.comune.rovereto.tn.it/openpa/object/131089", "abstract_text": "Ciclo di conferenze online &quot;Il filosofo e il coraggio della verit\u00e0&quot;", "abstract": "<p>Ciclo di conferenze online &quot;Il filosofo e il coraggio della verit\u00e0&quot;</p>", "title": "Finzione e verit\u00e0. Foucault", "lon": "11.043781", "modifica": "2021-04-08", "link": "http://www.comune.rovereto.tn.it/api/opendata/v2/content/read/131089", "lat": "45.89106", "duration_days": "[datetime.date(2021, 4, 15), datetime.date(2021, 4, 19)]", "duration_hours": "()", "weekday": "['gioved\u00ec']", "indirizzo": "['dalle', 'alle', 'Webinar', '|', 'Piattaforma', 'Zoom']", "repeated": "False", "ticket": [], "is_online": false, "is_offline": false, "is_blended": false}