{
    "name": "didattica2021mart-blabla-incontri-in-lingua-straniera_73112.",
    "links": [
        "#",
        "mailto:education@mart.tn.iteducation@mart.tn.it/a",
        "http://www.mart.trento.it",
        "/it/mostre/mart.html"
    ],
    "location": [
        "Dove:",
        "itemprop=streetAddressMart,",
        "Corso",
        "Bettini,",
        "Rovereto",
        "(Tn)",
        "Orario:",
        "Venerdì",
        "22",
        "ottobre",
        "2021,",
        "ore",
        "18.00-19.30,",
        "Mart",
        "Rovereto:",
        "Mart",
        "Bla",
        "Bla",
        "English;",
        "Venerdì",
        "29",
        "ottobre",
        "2021,",
        "ore",
        "18.00-19.30,",
        "Mart",
        "Rovereto:",
        "Mart",
        "Bla",
        "Bla",
        "Deutsch",
        "Note:",
        "Costo:",
        "",
        "5",
        "/",
        "I",
        "docenti",
        "possono",
        "richiedere",
        "lattestato",
        "di",
        "frequenza",
        "valido",
        "ai",
        "fini",
        "dellaggiornamento.",
        "Prenotazione",
        "consigliata",
        "entro",
        "le",
        "ore",
        "12.00",
        "del",
        "venerdì",
        "precedente:",
        "T",
        "0464.454108-151",
        "o",
        "a",
        "href=mailto:education@mart.tn.iteducation@mart.tn.it/a",
        "Sito",
        "web:",
        "a",
        "href=http://www.mart.trento.it",
        "target=_blankwww.mart.trento.it/"
    ],
    "duration_hours": [
        "18.00-19.30,",
        "18.00-19.30,"
    ],
    "duration_days": "Not specified",
    "schema": [
        "itemtype=http://schema.org/Place",
        "itemtype=http://schema.org/PostalAddress"
    ]
}