{"has_eventID": "", "has_title": "L\u2019inchiesta spezzata. Perch\u00e9 hanno ucciso Pier Paolo Pasolini", "has_type": "", "has_mode": "offline", "has_cost": {"has_ticketID": "", "has_event": "", "has_freeEntrance": false, "has_onlineBooking": false, "has_extraBenefits": "", "has_totalPurchase": 0, "has_price": "https://www.comune.rovereto.tn.it/openpa/object/128585", "has_currency": "EUR", "has_purchaser": null}, "has_link": "https://www.comune.rovereto.tn.it/openpa/object/128585", "has_targetAge": "", "has_edition": 0, "has_festivalStatus": false, "has_language": ["it-IT"], "has_start": "2020/11/20 06:30:00  AM", "has_end": "2020/11/27 12:00:00  PM", "has_recurrency": "False", "has_organizer": "", "has_specialAnnouncements": "", "has_description": "Dialogo con Simona Zecchi, giornalista di inchiesta e autrice di due libri sulla morte di Pasolini", "has_terminated": true, "has_hashtag": [], "has_distance": false, "has_schedule": "weekly", "has_transportMode": [], "has_venue": "    Diretta  su  Instagram", "has_virtualLocation": "", "has_superEvent": ""}